pynoisetn/__init__.py
pynoisetn-0.3.0.dist-info/METADATA
pynoisetn-0.3.0.dist-info/WHEEL
pynoisetn-0.3.0.dist-info/RECORD
