Metadata-Version: 2.1
Name: pynoisetn
Version: 0.3.0
Summary: tolls discord
Author: ykg
Author-email: ykggnitrosetc@gmail.com
Requires-Python: >=3.10,<4.0
Classifier: Programming Language :: Python :: 3
Classifier: Programming Language :: Python :: 3.10
Classifier: Programming Language :: Python :: 3.11
